hello_agents/__init__.py
hello_agents/version.py
hello_agents/agents/__init__.py
hello_agents/agents/plan_solve_agent.py
hello_agents/agents/react_agent.py
hello_agents/agents/reflection_agent.py
hello_agents/agents/simple_agent.py
hello_agents/context/__init__.py
hello_agents/context/builder.py
hello_agents/core/__init__.py
hello_agents/core/agent.py
hello_agents/core/config.py
hello_agents/core/database_config.py
hello_agents/core/exceptions.py
hello_agents/core/llm.py
hello_agents/core/message.py
hello_agents/evaluation/__init__.py
hello_agents/evaluation/benchmarks/__init__.py
hello_agents/evaluation/benchmarks/bfcl/__init__.py
hello_agents/evaluation/benchmarks/bfcl/bfcl_integration.py
hello_agents/evaluation/benchmarks/bfcl/dataset.py
hello_agents/evaluation/benchmarks/bfcl/evaluator.py
hello_agents/evaluation/benchmarks/bfcl/metrics.py
hello_agents/evaluation/benchmarks/data_generation/__init__.py
hello_agents/evaluation/benchmarks/data_generation/dataset.py
hello_agents/evaluation/benchmarks/data_generation/llm_judge.py
hello_agents/evaluation/benchmarks/data_generation/win_rate.py
hello_agents/evaluation/benchmarks/gaia/__init__.py
hello_agents/evaluation/benchmarks/gaia/dataset.py
hello_agents/evaluation/benchmarks/gaia/evaluator.py
hello_agents/evaluation/benchmarks/gaia/metrics.py
hello_agents/memory/__init__.py
hello_agents/memory/base.py
hello_agents/memory/embedding.py
hello_agents/memory/manager.py
hello_agents/memory/rag/__init__.py
hello_agents/memory/rag/document.py
hello_agents/memory/rag/pipeline.py
hello_agents/memory/storage/__init__.py
hello_agents/memory/storage/document_store.py
hello_agents/memory/storage/neo4j_store.py
hello_agents/memory/storage/qdrant_store.py
hello_agents/memory/types/__init__.py
hello_agents/memory/types/episodic.py
hello_agents/memory/types/perceptual.py
hello_agents/memory/types/semantic.py
hello_agents/memory/types/working.py
hello_agents/protocols/__init__.py
hello_agents/protocols/base.py
hello_agents-0.2.7.dist-info/licenses/LICENSE
hello_agents-0.2.7.dist-info/METADATA
hello_agents-0.2.7.dist-info/WHEEL
hello_agents-0.2.7.dist-info/top_level.txt
hello_agents-0.2.7.dist-info/RECORD
