Metadata-Version: 2.4
Name: hello-agents
Version: 0.2.7
Summary: 灵活、可扩展的多智能体框架 - 基于OpenAI原生API
Author-email: HelloAgents Team <jjyaoao@126.com>
License: CC-BY-NC-SA-4.0
Project-URL: Homepage, https://github.com/jjyaoao/HelloAgents
Project-URL: Documentation, https://github.com/jjyaoao/HelloAgents/blob/main/README.md
Project-URL: Repository, https://github.com/jjyaoao/HelloAgents
Project-URL: Bug Tracker, https://github.com/jjyaoao/HelloAgents/issues
Requires-Python: >=3.10
License-File: LICENSE
Requires-Dist: openai<2.0.0,>=1.0.0
Requires-Dist: requests<3.0.0,>=2.25.0
Requires-Dist: python-dotenv<2.0.0,>=0.19.0
Requires-Dist: pydantic<3.0.0,>=2.0.0
Requires-Dist: beautifulsoup4<5.0.0,>=4.9.0
Requires-Dist: numpy<3.0.0,>=2.0.0
Requires-Dist: networkx<4.0.0,>=2.6.0
Requires-Dist: tiktoken>=0.5.0
Provides-Extra: search
Requires-Dist: tavily-python>=0.7.12; extra == "search"
Requires-Dist: google-search-results>=2.4.2; extra == "search"
Provides-Extra: memory
Requires-Dist: qdrant-client>=1.6.0; extra == "memory"
Requires-Dist: neo4j>=5.0.0; extra == "memory"
Requires-Dist: spacy>=3.4.0; extra == "memory"
Requires-Dist: scikit-learn>=1.0.0; extra == "memory"
Provides-Extra: rag
Requires-Dist: scikit-learn>=1.0.0; extra == "rag"
Requires-Dist: transformers>=4.20.0; extra == "rag"
Requires-Dist: torch>=1.12.0; extra == "rag"
Requires-Dist: sentence-transformers>=2.2.0; extra == "rag"
Requires-Dist: markitdown>=0.0.1; extra == "rag"
Requires-Dist: pypdf>=3.9.0; extra == "rag"
Requires-Dist: pdfminer.six>=20221105; extra == "rag"
Provides-Extra: protocols
Requires-Dist: fastmcp<3.0.0,>=2.0.0; extra == "protocols"
Requires-Dist: a2a-sdk>=0.1.0; extra == "protocols"
Provides-Extra: evaluation
Requires-Dist: datasets>=2.14.0; extra == "evaluation"
Requires-Dist: huggingface_hub<1.0.0,>=0.20.0; extra == "evaluation"
Requires-Dist: evaluate<1.0.0,>=0.4.0; extra == "evaluation"
Requires-Dist: pandas<3.0.0,>=2.0.0; extra == "evaluation"
Requires-Dist: matplotlib<4.0.0,>=3.7.0; extra == "evaluation"
Requires-Dist: seaborn<1.0.0,>=0.12.0; extra == "evaluation"
Requires-Dist: tqdm<5.0.0,>=4.65.0; extra == "evaluation"
Requires-Dist: gradio<5.0.0,>=4.0.0; extra == "evaluation"
Provides-Extra: rl
Requires-Dist: trl>=0.24.0; extra == "rl"
Requires-Dist: transformers>=4.20.0; extra == "rl"
Requires-Dist: torch>=2.0.0; extra == "rl"
Requires-Dist: datasets>=2.14.0; extra == "rl"
Requires-Dist: accelerate>=0.20.0; extra == "rl"
Requires-Dist: peft>=0.5.0; extra == "rl"
Requires-Dist: bitsandbytes>=0.41.0; extra == "rl"
Requires-Dist: wandb>=0.15.0; extra == "rl"
Requires-Dist: tensorboard>=2.13.0; extra == "rl"
Provides-Extra: memory-rag
Requires-Dist: hello-agents[memory,rag]; extra == "memory-rag"
Provides-Extra: all
Requires-Dist: hello-agents[evaluation,memory-rag,protocols,rl,search]; extra == "all"
Dynamic: license-file
Dynamic: requires-python
